ud_distributions/Binomialdistribution.py
ud_distributions/Gaussiandistribution.py
ud_distributions/Generaldistribution.py
ud_distributions/__init__.py
ud_distributions-0.1.dist-info/DESCRIPTION.rst
ud_distributions-0.1.dist-info/METADATA
ud_distributions-0.1.dist-info/RECORD
ud_distributions-0.1.dist-info/WHEEL
ud_distributions-0.1.dist-info/metadata.json
ud_distributions-0.1.dist-info/top_level.txt
